[
 {
  "_assign": null, 
  "_comments": null, 
  "_liked_by": null, 
  "_user_tags": null, 
  "default_value": null, 
  "doc_type": "Supplier Quotation", 
  "docstatus": 0, 
  "doctype": "Property Setter", 
  "doctype_or_field": "DocField", 
  "field_name": "naming_series", 
  "modified": "2017-04-10 15:22:27.453674", 
  "name": "Supplier Quotation-naming_series-options", 
  "property": "options", 
  "property_type": "Text", 
  "value": "SQTN-\nSQTN-RM-.####\nSQTN-PM-.####\nSQTN-ENGG-ELEC-.####\nSQTN-ENGG-MECH-.####\nSQTN-OTH-.####"
 }, 
 {
  "_assign": null, 
  "_comments": null, 
  "_liked_by": null, 
  "_user_tags": null, 
  "default_value": null, 
  "doc_type": "Purchase Order", 
  "docstatus": 0, 
  "doctype": "Property Setter", 
  "doctype_or_field": "DocField", 
  "field_name": "naming_series", 
  "modified": "2017-04-10 15:23:08.355631", 
  "name": "Purchase Order-naming_series-options", 
  "property": "options", 
  "property_type": "Text", 
  "value": "PO\nPO-RM-.####\nPO-PM-.####\nPO-ENGG-ELEC-.####\nPO-ENGG-MECH-.####\nPO-OTH-.####"
 }, 
 {
  "_assign": null, 
  "_comments": null, 
  "_liked_by": null, 
  "_user_tags": null, 
  "default_value": null, 
  "doc_type": "Purchase Receipt", 
  "docstatus": 0, 
  "doctype": "Property Setter", 
  "doctype_or_field": "DocField", 
  "field_name": "naming_series", 
  "modified": "2017-04-10 15:52:01.034264", 
  "name": "Purchase Receipt-naming_series-options", 
  "property": "options", 
  "property_type": "Text", 
  "value": "PREC-\nPREC-RET-\nPREC-RM.-####\nPREC-PM.-####\nPREC-ENGG-ELEC-.####\nPREC-ENGG-MECH-.####\nPREC-OTH-.####"
 }
]